plot_agent/__init__.py
plot_agent/agent.py
plot_agent/execution.py
plot_agent/models.py
plot_agent/prompt.py
plot_agent-0.4.0.dist-info/licenses/LICENSE
plot_agent-0.4.0.dist-info/METADATA
plot_agent-0.4.0.dist-info/WHEEL
plot_agent-0.4.0.dist-info/top_level.txt
plot_agent-0.4.0.dist-info/RECORD
