Metadata-Version: 2.4
Name: plot-agent
Version: 0.4.0
Summary: An AI-powered data visualization assistant using Plotly
Author-email: andrewm4894 <andrewm4894@gmail.com>
Project-URL: Homepage, https://github.com/andrewm4894/plot-agent
Classifier: Programming Language :: Python :: 3
Classifier: License :: OSI Approved :: MIT License
Classifier: Operating System :: OS Independent
Requires-Python: >=3.8
License-File: LICENSE
Dynamic: license-file
